arcade_arcade_engine_api/__init__.py
arcade_arcade_engine_api/tools/__init__.py
arcade_arcade_engine_api/tools/request_body_schemas.py
arcade_arcade_engine_api/wrapper_tools/AuthorizeUserToolAccess.json
arcade_arcade_engine_api/wrapper_tools/AuthorizeWorker.json
arcade_arcade_engine_api/wrapper_tools/CheckArcadeEngineHealth.json
arcade_arcade_engine_api/wrapper_tools/CheckAuthStatus.json
arcade_arcade_engine_api/wrapper_tools/CreateWorker.json
arcade_arcade_engine_api/wrapper_tools/DeleteAuthProvider.json
arcade_arcade_engine_api/wrapper_tools/DeleteMcpEndpoint.json
arcade_arcade_engine_api/wrapper_tools/DeleteSecretById.json
arcade_arcade_engine_api/wrapper_tools/DeleteUserAuthConnection.json
arcade_arcade_engine_api/wrapper_tools/DeleteWorker.json
arcade_arcade_engine_api/wrapper_tools/ExecuteTool.json
arcade_arcade_engine_api/wrapper_tools/FetchToolsPage.json
arcade_arcade_engine_api/wrapper_tools/GetAuthProviderDetails.json
arcade_arcade_engine_api/wrapper_tools/GetFormattedToolSpecification.json
arcade_arcade_engine_api/wrapper_tools/GetOpenAPISpecification.json
arcade_arcade_engine_api/wrapper_tools/GetProjectDetails.json
arcade_arcade_engine_api/wrapper_tools/GetScheduledToolDetails.json
arcade_arcade_engine_api/wrapper_tools/GetScheduledToolExecutions.json
arcade_arcade_engine_api/wrapper_tools/GetToolSpecification.json
arcade_arcade_engine_api/wrapper_tools/GetToolsList.json
arcade_arcade_engine_api/wrapper_tools/GetWorkerById.json
arcade_arcade_engine_api/wrapper_tools/GetWorkerHealthStatus.json
arcade_arcade_engine_api/wrapper_tools/ListAccessibleProjects.json
arcade_arcade_engine_api/wrapper_tools/ListAuthConnections.json
arcade_arcade_engine_api/wrapper_tools/ListAvailableAuthProviders.json
arcade_arcade_engine_api/wrapper_tools/ListWorkers.json
arcade_arcade_engine_api/wrapper_tools/RetrieveFormattedToolsList.json
arcade_arcade_engine_api/wrapper_tools/TestWorkerConnection.json
arcade_arcade_engine_api-1.0.0.dist-info/METADATA
arcade_arcade_engine_api-1.0.0.dist-info/WHEEL
arcade_arcade_engine_api-1.0.0.dist-info/entry_points.txt
arcade_arcade_engine_api-1.0.0.dist-info/licenses/LICENSE
arcade_arcade_engine_api-1.0.0.dist-info/RECORD
